mclbn256/lib/__init__.py
mclbn256/__init__.py
mclbn256/mclbn256.py
mclbn256-1.3.5.dist-info/METADATA
mclbn256-1.3.5.dist-info/WHEEL
mclbn256-1.3.5.dist-info/top_level.txt
mclbn256-1.3.5.dist-info/RECORD
mclbn256-1.3.5.dist-info/LICENSE