Metadata-Version: 2.1
Name: mclbn256
Version: 1.3.5
Summary: Python bindings for the BN254/256 pairing-friendly curve supported by the MCl library.
Home-page: https://github.com/nthparty/mclbn256
Author: Wyatt Howe
Author-email: Wyatt@nthparty.com
Project-URL: Bug Tracker, https://github.com/nthparty/mclbn256/issues
Classifier: Programming Language :: Python :: 3
Classifier: Operating System :: OS Independent
Classifier: License :: OSI Approved :: MIT License
Requires-Python: >=3.6
License-File: LICENSE
License: MIT
